auto_machine_learning/__init__.py
auto_machine_learning/constants.py
auto_machine_learning/utils.py
auto_machine_learning/automl/__init__.py
auto_machine_learning/automl/auto_model_trainer.py
auto_machine_learning/automl/automl.py
auto_machine_learning/data_preprocessing/__init__.py
auto_machine_learning/data_preprocessing/preprocessing.py
auto_machine_learning/datasets/__init__.py
auto_machine_learning/datasets/boston.csv
auto_machine_learning/datasets/carprice.csv
auto_machine_learning/datasets/diabetes.csv
auto_machine_learning/datasets/fitbit.csv
auto_machine_learning/datasets/heart_disease.csv
auto_machine_learning/datasets/load_dataset.py
auto_machine_learning/datasets/rain_australia.csv
auto_machine_learning/datasets/salary.csv
auto_machine_learning/datasets/solar.csv
auto_machine_learning/datasets/titanic.csv
auto_machine_learning/ensembling/__init__.py
auto_machine_learning/ensembling/super_learner.py
auto_machine_learning/feature_engineering/__init__.py
auto_machine_learning/feature_engineering/anova.py
auto_machine_learning/feature_engineering/correlation.py
auto_machine_learning/feature_engineering/pca.py
auto_machine_learning/feature_engineering/select_from_model.py
auto_machine_learning/hyperparameter_optimization/__init__.py
auto_machine_learning/hyperparameter_optimization/hpo.py
auto_machine_learning/hyperparameter_optimization/hpo_methods.py
auto_machine_learning/metrics/__init__.py
auto_machine_learning/metrics/metrics.py
auto_machine_learning/tests/__init__.py
auto_machine_learning/tests/AutoML/__init__.py
auto_machine_learning/tests/AutoML/test_auto_model_trainer.py
auto_machine_learning/tests/AutoML/test_automl.py
auto_machine_learning/tests/data_preprocessing/__init__.py
auto_machine_learning/tests/data_preprocessing/test_preprocessing.py
auto_machine_learning/tests/datasets/__init__.py
auto_machine_learning/tests/datasets/test_load_dataset.py
auto_machine_learning/tests/ensembling/__init__.py
Super_ML-0.0.3.dist-info/LICENSE
Super_ML-0.0.3.dist-info/METADATA
Super_ML-0.0.3.dist-info/WHEEL
Super_ML-0.0.3.dist-info/top_level.txt
Super_ML-0.0.3.dist-info/RECORD
